scivision/__init__.py
scivision/koala.py
scivision/catalog/__init__.py
scivision/catalog/catalog.py
scivision/catalog/check_datasets.py
scivision/catalog/check_models.py
scivision/catalog/gen_json_schema.py
scivision/catalog/data/datasources.json
scivision/catalog/data/models.json
scivision/catalog/data/projects.json
scivision/catalog/data/thumbnails/datasources/Parakeet.jpg
scivision/catalog/data/thumbnails/datasources/Phenotypic Profiling.jpg
scivision/catalog/data/thumbnails/datasources/Pixelflow Seed Demo Data.jpg
scivision/catalog/data/thumbnails/datasources/butterflies.jpg
scivision/catalog/data/thumbnails/datasources/cefas-plankton.jpg
scivision/catalog/data/thumbnails/datasources/cell-cycle-scivision.jpg
scivision/catalog/data/thumbnails/datasources/coastal-edges.jpg
scivision/catalog/data/thumbnails/datasources/fathomnet23.jpg
scivision/catalog/data/thumbnails/datasources/flowers.jpg
scivision/catalog/data/thumbnails/datasources/oppd-seedlings.jpg
scivision/catalog/data/thumbnails/datasources/scivision-test-data.jpg
scivision/catalog/data/thumbnails/datasources/seapens-detection.jpg
scivision/catalog/data/thumbnails/datasources/sentinel2_stac.jpg
scivision/catalog/data/thumbnails/datasources/stardist-cell-nuclei-2D.jpg
scivision/catalog/data/thumbnails/datasources/treecrowns.jpg
scivision/catalog/data/thumbnails/models/Affinity-VAE.jpg
scivision/catalog/data/thumbnails/models/PlantCV.jpg
scivision/catalog/data/thumbnails/models/StarDist Seed.jpg
scivision/catalog/data/thumbnails/models/btrack.jpg
scivision/catalog/data/thumbnails/models/butterfly-classification-model.jpg
scivision/catalog/data/thumbnails/models/canopy-quality.jpg
scivision/catalog/data/thumbnails/models/detectreeRGB-forest.jpg
scivision/catalog/data/thumbnails/models/flower-classification-model.jpg
scivision/catalog/data/thumbnails/models/greenotyper.jpg
scivision/catalog/data/thumbnails/models/huggingface-classifiers.jpg
scivision-0.7.4.dist-info/LICENSE
scivision-0.7.4.dist-info/METADATA
scivision-0.7.4.dist-info/WHEEL
scivision-0.7.4.dist-info/entry_points.txt
scivision-0.7.4.dist-info/top_level.txt
scivision-0.7.4.dist-info/RECORD
