Metadata-Version: 2.1
Name: scivision
Version: 0.7.4
Summary: Scivision
Maintainer-email: scivision@turing.ac.uk
License: BSD 3-Clause License
Project-URL: Homepage, https://sci.vision
Project-URL: Source, https://github.com/alan-turing-institute/scivision
Project-URL: Issue tracker, https://github.com/alan-turing-institute/scivision/issues
Requires-Python: >=3.7
License-File: LICENSE
Requires-Dist: matplotlib ~=3.6
Requires-Dist: numpy ~=1.23
Requires-Dist: scipy ~=1.9
Requires-Dist: pandas <3,>=1.5
Requires-Dist: fsspec >=2022.11
Requires-Dist: pyyaml ~=6.0
Requires-Dist: requests ~=2.28
Requires-Dist: aiohttp ~=3.8
Requires-Dist: intake ~=0.6
Requires-Dist: intake-xarray ~=0.6
Requires-Dist: pydantic ~=1.9
Requires-Dist: exifread ~=3.0
Requires-Dist: distinctipy ~=1.2
Requires-Dist: ipython ~=8.3
Requires-Dist: tqdm ~=4.65
Requires-Dist: netcdf4 <1.7
Provides-Extra: cloud_extra
Requires-Dist: scivision[gcs,s3] ; extra == 'cloud_extra'
Provides-Extra: dev
Requires-Dist: pre-commit ; extra == 'dev'
Provides-Extra: doc
Requires-Dist: sphinx ; extra == 'doc'
Requires-Dist: sphinx-rtd-theme ; extra == 'doc'
Requires-Dist: pydata-sphinx-theme ; extra == 'doc'
Requires-Dist: readthedocs-sphinx-search ; extra == 'doc'
Requires-Dist: m2r2 ; extra == 'doc'
Provides-Extra: gcs
Requires-Dist: gcsfs >=2022.02 ; extra == 'gcs'
Provides-Extra: s3
Requires-Dist: s3fs ; extra == 's3'
Provides-Extra: test
Requires-Dist: pytest ; extra == 'test'
